rubble/__init__.py
rubble/rubble.py
rubble/rubble_data.py
rubble-0.2.1.dist-info/LICENSE
rubble-0.2.1.dist-info/LICENSE.txt
rubble-0.2.1.dist-info/METADATA
rubble-0.2.1.dist-info/WHEEL
rubble-0.2.1.dist-info/top_level.txt
rubble-0.2.1.dist-info/RECORD
