Metadata-Version: 2.1
Name: rubble
Version: 0.2.1
Summary: An implicit code for simulating the local evolution of solid size distributions in protoplanetary disks
Home-page: https://github.com/astroboylrx/Rubble
Author: Rixin Li
Author-email: rixinli.astro@gmail.com
License: GPLv3+
Keywords: dust evolution,coagulation,Smoluchowski
Platform: UNKNOWN
Classifier: Development Status :: 4 - Beta
Classifier: Intended Audience :: Science/Research
Classifier: Topic :: Scientific/Engineering :: Astronomy
Classifier: License :: OSI Approved :: GNU General Public License v3 or later (GPLv3+)
Classifier: Programming Language :: Python :: 3
License-File: LICENSE
License-File: LICENSE.txt
Requires-Dist: numpy
Requires-Dist: scipy
Requires-Dist: matplotlib
Requires-Dist: astropy
Provides-Extra: dev
Requires-Dist: check-manifest ; extra == 'dev'
Provides-Extra: test
Requires-Dist: coverage ; extra == 'test'
